q_isa/__init__.py
qisa-0.0.0.dist-info/LICENSE
qisa-0.0.0.dist-info/METADATA
qisa-0.0.0.dist-info/WHEEL
qisa-0.0.0.dist-info/top_level.txt
qisa-0.0.0.dist-info/RECORD
